LICENSE
MANIFEST.in
README.rst
requirements.txt
setup.py
docs/datatypes.rst
docs/evaluation.rst
docs/implementation.rst
docs/index.rst
docs/input_conversion.rst
docs/installation.rst
docs/modules.rst
docs/reference.rst
docs/sentencepairscore.rst
docs/sequencealigner.rst
docs/svm.rst
docs/tokenizers.rst
docs/train_data_generation.rst
docs/tutorial.rst
docs/utils.rst
docs/wordpairscore.rst
docs/yalign.rst
docs/yalignmodel.rst
scripts/yalign-align
scripts/yalign-evaluate-alignment
scripts/yalign-evaluate-correlation
scripts/yalign-evaluate-model
scripts/yalign-evaluate-precision
scripts/yalign-freebase
scripts/yalign-phrasetable-csv
scripts/yalign-train
tests/helpers.py
tests/test_evaluation.py
tests/test_input_conversion.py
tests/test_sentencepairscore.py
tests/test_sequencealigner.py
tests/test_train_data_generation.py
tests/test_wordpairscore.py
tests/test_yalignmodel.py
yalign/__init__.py
yalign/datatypes.py
yalign/evaluation.py
yalign/input_conversion.py
yalign/sentencepairscore.py
yalign/sequencealigner.py
yalign/svm.py
yalign/tokenizers.py
yalign/train_data_generation.py
yalign/utils.py
yalign/wordpairscore.py
yalign/yalignmodel.py
yalign.egg-info/PKG-INFO
yalign.egg-info/SOURCES.txt
yalign.egg-info/dependency_links.txt
yalign.egg-info/requires.txt
yalign.egg-info/top_level.txt