Metadata-Version: 1.1
Name: yalign
Version: 0.1.1
Summary: A tool to align comparable corpora
Home-page: https://github.com/machinalis/yalign
Author: Rafael Carrascosa, Gonzalo Garcia Berrotaran, Andrew Vine
Author-email: rafacarrascosa@gmail.com
License: UNKNOWN
Keywords: align,corpus,corpus alignment
Platform: UNKNOWN
Classifier: Programming Language :: Python
Classifier: Development Status :: 3 - Alpha
Classifier: Intended Audience :: Developers
Classifier: Natural Language :: English
Classifier: License :: OSI Approved :: BSD License
Classifier: Operating System :: OS Independent
Classifier: Topic :: Scientific/Engineering :: Human Machine Interfaces
Classifier: Topic :: Scientific/Engineering :: Interface Engine/Protocol Translator
Classifier: Topic :: Text Processing :: Linguistic
Classifier: Topic :: Text Processing
Classifier: Topic :: Utilities
